sneiaTools/__init__.py
sneiaTools/biomedical/__init__.py
sneiaTools/biomedical/biomedical.py
sneiaTools/metrics/__init__.py
sneiaTools/metrics/metrics.py
sneiaTools-0.0.4.dist-info/LICENSE
sneiaTools-0.0.4.dist-info/METADATA
sneiaTools-0.0.4.dist-info/WHEEL
sneiaTools-0.0.4.dist-info/top_level.txt
sneiaTools-0.0.4.dist-info/RECORD
