Metadata-Version: 2.1
Name: sneiaTools
Version: 0.0.4
Summary: A python package that will include all the tools that the SNEIA research team will develop and need to carry out their tasks.
Home-page: https://github.com/Semillero-de-neuroinformatica/SNEIA-tools
Author: SNEIA Research Team
Author-email: sneia@utp.edu.co
License: MIT
License-File: LICENSE
Requires-Dist: numpy
Requires-Dist: matplotlib
Requires-Dist: pandas
Requires-Dist: mne
Requires-Dist: scipy
Requires-Dist: scikit-learn
